mhc/__init__.py
mhc/config.py
mhc/presets.py
mhc/version.py
mhc/constraints/__init__.py
mhc/constraints/identity.py
mhc/constraints/matrix.py
mhc/constraints/simplex.py
mhc/layers/__init__.py
mhc/layers/conv_mhc.py
mhc/layers/history_buffer.py
mhc/layers/managed.py
mhc/layers/matrix_skip.py
mhc/layers/mhc_skip.py
mhc/tf/__init__.py
mhc/tf/constraints.py
mhc/tf/graph.py
mhc/tf/layers.py
mhc/utils/__init__.py
mhc/utils/compat.py
mhc/utils/decorators.py
mhc/utils/injection.py
mhc/utils/lightning_callback.py
mhc/utils/logging.py
mhc/utils/profiling.py
mhc/utils/seed.py
mhc/utils/tensor_ops.py
mhc/utils/visualization.py
mhc-0.5.5.dist-info/licenses/LICENSE
mhc-0.5.5.dist-info/METADATA
mhc-0.5.5.dist-info/WHEEL
mhc-0.5.5.dist-info/top_level.txt
mhc-0.5.5.dist-info/RECORD
