Metadata-Version: 2.4
Name: mhc
Version: 0.5.5
Summary: Manifold-Constrained Hyper-Connections: Stable multi-history skip connections for deep neural networks.
Author-email: gm24med <simogouali49@gmail.com>
License: MIT
Project-URL: Homepage, https://gm24med.github.io/MHC/
Project-URL: Repository, https://github.com/gm24med/MHC
Project-URL: Issues, https://github.com/gm24med/MHC/issues
Project-URL: Documentation, https://gm24med.github.io/MHC/
Keywords: pytorch,deep-learning,skip-connections,stability,manifold-learning
Classifier: Development Status :: 4 - Beta
Classifier: Intended Audience :: Science/Research
Classifier: Topic :: Scientific/Engineering :: Artificial Intelligence
Classifier: License :: OSI Approved :: MIT License
Classifier: Programming Language :: Python :: 3.11
Classifier: Programming Language :: Python :: 3.12
Classifier: Programming Language :: Python :: 3.13
Requires-Python: >=3.11
License-File: LICENSE
Requires-Dist: torch>=2.0.0
Requires-Dist: numpy
Provides-Extra: dev
Requires-Dist: pytest>=7.0; extra == "dev"
Requires-Dist: ruff>=0.14.13; extra == "dev"
Requires-Dist: mypy>=1.0.0; extra == "dev"
Requires-Dist: pre-commit>=3.0.0; extra == "dev"
Requires-Dist: matplotlib>=3.5.0; extra == "dev"
Requires-Dist: mkdocs>=1.5.0; extra == "dev"
Requires-Dist: mkdocs-material>=9.0.0; extra == "dev"
Requires-Dist: mkdocstrings[python]>=0.23.0; extra == "dev"
Provides-Extra: tf
Requires-Dist: tensorflow>=2.12; extra == "tf"
Requires-Dist: keras>=3.13.1; extra == "tf"
Provides-Extra: viz
Requires-Dist: matplotlib>=3.5.0; extra == "viz"
Provides-Extra: config
Requires-Dist: tomli>=2.0.0; python_version < "3.11" and extra == "config"
Dynamic: license-file
